Metadata-Version: 1.1
Name: python-xml2dict
Version: 0.1.1
Summary: Flexible XML to dict Converter
Home-page: https://github.com/gotthardp/python-xml2dict.git
Author: Petr Gotthard
Author-email: petr.gotthard@centrum.cz
License: UNKNOWN
Platform: UNKNOWN
Classifier: Programming Language :: Python :: 3
Classifier: License :: OSI Approved :: MIT License
Classifier: Development Status :: 4 - Beta
